nlp_mitb_2025/__init__.py
nlp_mitb_2025/nlp.py
nlp_package_mitb_2025-0.1.0.dist-info/METADATA
nlp_package_mitb_2025-0.1.0.dist-info/WHEEL
nlp_package_mitb_2025-0.1.0.dist-info/top_level.txt
nlp_package_mitb_2025-0.1.0.dist-info/RECORD
