Metadata-Version: 2.2
Name: nlp_package_mitb_2025
Version: 0.1.0
Summary: A Python package for various NLP utilities.
Author: Your Name
Author-email: your.email@example.com
Classifier: Programming Language :: Python :: 3
Classifier: Operating System :: OS Independent
Requires-Python: >=3.6
Requires-Dist: nltk>=3.6.0
Dynamic: author
Dynamic: author-email
Dynamic: classifier
Dynamic: requires-dist
Dynamic: requires-python
Dynamic: summary
